Metadata-Version: 2.1
Name: varuacademyatools
Version: 0.1.0
Summary: This is a package created to includes tools used by Students of Vaaru Academy
Author: Vaaru Academy
Author-email: vaaruacademy@gmail.com
License: MIT
License-File: LICENSE
